duHast/__init__.py
duHast/Data/__init__.py
duHast/Data/data_to_shapely.py
duHast/Data/process_ceilings_to_rooms.py
duHast/Data/Objects/__init__.py
duHast/Data/Objects/BluePrints/__init__.py
duHast/Data/Objects/BluePrints/blueprint_property_names.py
duHast/Data/Objects/BluePrints/room_layout_sheets.py
duHast/Data/Objects/Collectors/__init__.py
duHast/Data/Objects/Collectors/data_base.py
duHast/Data/Objects/Collectors/data_ceiling.py
duHast/Data/Objects/Collectors/data_door.py
duHast/Data/Objects/Collectors/data_family_base.py
duHast/Data/Objects/Collectors/data_level_building.py
duHast/Data/Objects/Collectors/data_room.py
duHast/Data/Objects/Collectors/data_sheet.py
duHast/Data/Objects/Collectors/data_sheet_view_port.py
duHast/Data/Objects/Collectors/data_tag.py
duHast/Data/Objects/Collectors/data_view_3d.py
duHast/Data/Objects/Collectors/data_view_base.py
duHast/Data/Objects/Collectors/data_view_elevation.py
duHast/Data/Objects/Collectors/data_view_plan.py
duHast/Data/Objects/Collectors/data_view_schedule.py
duHast/Data/Objects/Collectors/Properties/__init__.py
duHast/Data/Objects/Collectors/Properties/data_design_set_option.py
duHast/Data/Objects/Collectors/Properties/data_element_geometry_base.py
duHast/Data/Objects/Collectors/Properties/data_instance_properties.py
duHast/Data/Objects/Collectors/Properties/data_level.py
duHast/Data/Objects/Collectors/Properties/data_level_base.py
duHast/Data/Objects/Collectors/Properties/data_phasing.py
duHast/Data/Objects/Collectors/Properties/data_property.py
duHast/Data/Objects/Collectors/Properties/data_property_names.py
duHast/Data/Objects/Collectors/Properties/data_revit_model.py
duHast/Data/Objects/Collectors/Properties/data_schedule_segement.py
duHast/Data/Objects/Collectors/Properties/data_sheet_size.py
duHast/Data/Objects/Collectors/Properties/data_sheet_size_names.py
duHast/Data/Objects/Collectors/Properties/data_type_properties.py
duHast/Data/Objects/Collectors/Properties/data_view_port_type_names.py
duhast-1.2.2.dist-info/METADATA
duhast-1.2.2.dist-info/WHEEL
duhast-1.2.2.dist-info/top_level.txt
duhast-1.2.2.dist-info/RECORD
