Metadata-Version: 2.4
Name: duhast
Version: 1.2.2
Summary: Sample code for Revit batch processing and the Revit API.
Author: Jan Christel
Author-email: duhast <jan.r.christel@gmail.com>
License: BSD-3-Clause
Project-URL: Homepage, https://github.com/jchristel/SampleCodeRevitBatchProcessor
Requires-Python: >=3.4
Dynamic: requires-python
